[
  {
    "id": 1,
    "name": "Clementina DuBuque",
    "username": "Moriah.Stanton",
    "email": "Rey.Padberg@karina.biz",
    "address": {
      "street": "Kattie Turnpike",
      "suite": "Suite 198",
      "city": "Lebsackbury",
      "zipcode": "31428-2261",
      "geo": {
        "lat": "-38.2386",
        "lng": "57.2232"
      }
    },
    "phone": "024-648-3804",
    "websit": "ambrose.net",
    "company": {
      "name": "Hoeger LLC",
      "catchPhrase": "Centralized empowering task-force",
      "bs": "target end-to-end models"
    }
  },
  {
    "id": 2,
    "name": "Clementina DuBuque2",
    "username": "Moriah.Stanton",
    "email": "Rey.Padberg@karina.biz",
    "address": {
      "street": "Kattie Turnpike",
      "suite": "Suite 198",
      "city": "Lebsackbury",
      "zipcode": "31428-2261",
      "geo": {
        "lat": "-38.2386",
        "lng": "57.2232"
      }
    },
    "phone": "024-648-3804",
    "websit": "ambrose.net",
    "company": {
      "name": "Hoeger LLC",
      "catchPhrase": "Centralized empowering task-force",
      "bs": "target end-to-end models"
    }
  }
]